<?xml version='1.0'?>
<ns2:test-suite xmlns:ns2='urn:model.allure.qatools.yandex.ru' start='1672829320688' stop='1672829337103'>
    <name>login:</name>
    <title>login:</title>
    <test-cases>
        <test-case start='1672829321223' status='passed' stop='1672829337094'>
            <name>PretaaLogin_test</name>
            <title>PretaaLogin_test</title>
            <labels/>
            <parameters/>
            <steps>
                <step start='1672829321479' status='passed' stop='1672829322888'>
                    <name>I am on page "/login"</name>
                    <title>I am on page "/login"</title>
                    <attachments/>
                    <steps/>
                </step>
                <step start='1672829322889' status='passed' stop='1672829322898'>
                    <name>I see "Continue"</name>
                    <title>I see "Continue"</title>
                    <attachments/>
                    <steps/>
                </step>
                <step start='1672829322899' status='passed' stop='1672829323384'>
                    <name>I fill field "[data-testid="email"]", "jiniya+1+admin@itobuz.com"</name>
                    <title>I fill field "[data-testid="email"]", "jiniya+1+admin@itobuz.com"</title>
                    <attachments/>
                    <steps/>
                </step>
                <step start='1672829323385' status='passed' stop='1672829323607'>
                    <name>I click "[data-testid="continue-btn"]"</name>
                    <title>I click "[data-testid="continue-btn"]"</title>
                    <attachments/>
                    <steps/>
                </step>
                <step start='1672829323608' status='passed' stop='1672829326160'>
                    <name>I fill field "[data-testid="password"]", "Password@50"</name>
                    <title>I fill field "[data-testid="password"]", "Password@50"</title>
                    <attachments/>
                    <steps/>
                </step>
                <step start='1672829326160' status='passed' stop='1672829326176'>
                    <name>I see "Show Password"</name>
                    <title>I see "Show Password"</title>
                    <attachments/>
                    <steps/>
                </step>
                <step start='1672829326176' status='passed' stop='1672829327178'>
                    <name>I wait 1</name>
                    <title>I wait 1</title>
                    <attachments/>
                    <steps/>
                </step>
                <step start='1672829327178' status='passed' stop='1672829327308'>
                    <name>I click "[type="button"]"</name>
                    <title>I click "[type="button"]"</title>
                    <attachments/>
                    <steps/>
                </step>
                <step start='1672829327309' status='passed' stop='1672829327475'>
                    <name>I click "[data-testid="submit-btn"]"</name>
                    <title>I click "[data-testid="submit-btn"]"</title>
                    <attachments/>
                    <steps/>
                </step>
                <step start='1672829327476' status='passed' stop='1672829330476'>
                    <name>I wait 3</name>
                    <title>I wait 3</title>
                    <attachments/>
                    <steps/>
                </step>
                <step start='1672829330476' status='passed' stop='1672829330624'>
                    <name>I click "[href="/settings/preferences/profile"]"</name>
                    <title>I click "[href="/settings/preferences/profile"]"</title>
                    <attachments/>
                    <steps/>
                </step>
                <step start='1672829330624' status='passed' stop='1672829330757'>
                    <name>I click ".pl-4 div:nth-child(4) h3"</name>
                    <title>I click ".pl-4 div:nth-child(4) h3"</title>
                    <attachments/>
                    <steps/>
                </step>
                <step start='1672829330757' status='passed' stop='1672829332760'>
                    <name>I wait 2</name>
                    <title>I wait 2</title>
                    <attachments/>
                    <steps/>
                </step>
                <step start='1672829332760' status='passed' stop='1672829332918'>
                    <name>I click "[href="/settings/admin/user-list"]"</name>
                    <title>I click "[href="/settings/admin/user-list"]"</title>
                    <attachments/>
                    <steps/>
                </step>
                <step start='1672829332918' status='passed' stop='1672829334919'>
                    <name>I wait 2</name>
                    <title>I wait 2</title>
                    <attachments/>
                    <steps/>
                </step>
                <step start='1672829334919' status='passed' stop='1672829335092'>
                    <name>I click "[href="/settings/admin/user-groups"]"</name>
                    <title>I click "[href="/settings/admin/user-groups"]"</title>
                    <attachments/>
                    <steps/>
                </step>
                <step start='1672829335092' status='passed' stop='1672829337093'>
                    <name>I wait 2</name>
                    <title>I wait 2</title>
                    <attachments/>
                    <steps/>
                </step>
            </steps>
            <attachments/>
        </test-case>
    </test-cases>
</ns2:test-suite>