<?xml version='1.0'?>
<ns2:test-suite xmlns:ns2='urn:model.allure.qatools.yandex.ru' start='1672136476081' stop='1672136501343'>
    <name>pretaacomments_test:</name>
    <title>pretaacomments_test:</title>
    <test-cases>
        <test-case start='1672136476481' status='passed' stop='1672136483723'>
            <name>Invalid email validation</name>
            <title>Invalid email validation</title>
            <labels/>
            <parameters/>
            <steps>
                <step start='1672136477375' status='passed' stop='1672136478756'>
                    <name>I am on page "/login"</name>
                    <title>I am on page "/login"</title>
                    <attachments/>
                    <steps/>
                </step>
                <step start='1672136478757' status='passed' stop='1672136479122'>
                    <name>I fill field "[data-testid="email"]", "123@itobuz.com"</name>
                    <title>I fill field "[data-testid="email"]", "123@itobuz.com"</title>
                    <attachments/>
                    <steps/>
                </step>
                <step start='1672136479122' status='passed' stop='1672136479307'>
                    <name>I click "[data-testid="continue-btn"]"</name>
                    <title>I click "[data-testid="continue-btn"]"</title>
                    <attachments/>
                    <steps/>
                </step>
                <step start='1672136479308' status='passed' stop='1672136481594'>
                    <name>I see element "[data-testid="error-id"]"</name>
                    <title>I see element "[data-testid="error-id"]"</title>
                    <attachments/>
                    <steps/>
                </step>
                <step start='1672136481594' status='passed' stop='1672136483597'>
                    <name>I wait 2</name>
                    <title>I wait 2</title>
                    <attachments/>
                    <steps/>
                </step>
                <step start='1672136483597' status='passed' stop='1672136483723'>
                    <name>I clear field "[data-testid="email"]"</name>
                    <title>I clear field "[data-testid="email"]"</title>
                    <attachments/>
                    <steps/>
                </step>
            </steps>
            <attachments/>
        </test-case>
        <test-case start='1672136483730' status='passed' stop='1672136489670'>
            <name>Password field blank validation</name>
            <title>Password field blank validation</title>
            <labels/>
            <parameters/>
            <steps>
                <step start='1672136483736' status='passed' stop='1672136484141'>
                    <name>I fill field "[data-testid="email"]", "admin@itobuz.com"</name>
                    <title>I fill field "[data-testid="email"]", "admin@itobuz.com"</title>
                    <attachments/>
                    <steps/>
                </step>
                <step start='1672136484141' status='passed' stop='1672136484291'>
                    <name>I click "[data-testid="continue-btn"]"</name>
                    <title>I click "[data-testid="continue-btn"]"</title>
                    <attachments/>
                    <steps/>
                </step>
                <step start='1672136484291' status='passed' stop='1672136486293'>
                    <name>I wait 2</name>
                    <title>I wait 2</title>
                    <attachments/>
                    <steps/>
                </step>
                <step start='1672136486294' status='passed' stop='1672136486465'>
                    <name>I click "[data-testid="submit-btn"]"</name>
                    <title>I click "[data-testid="submit-btn"]"</title>
                    <attachments/>
                    <steps/>
                </step>
                <step start='1672136486465' status='passed' stop='1672136487544'>
                    <name>I see element "[data-testid="error-id"]"</name>
                    <title>I see element "[data-testid="error-id"]"</title>
                    <attachments/>
                    <steps/>
                </step>
                <step start='1672136487544' status='passed' stop='1672136489544'>
                    <name>I wait 2</name>
                    <title>I wait 2</title>
                    <attachments/>
                    <steps/>
                </step>
                <step start='1672136489545' status='passed' stop='1672136489670'>
                    <name>I clear field "[data-testid="email"]"</name>
                    <title>I clear field "[data-testid="email"]"</title>
                    <attachments/>
                    <steps/>
                </step>
            </steps>
            <attachments/>
        </test-case>
        <test-case start='1672136489676' status='passed' stop='1672136494716'>
            <name>Email field blank validation</name>
            <title>Email field blank validation</title>
            <labels/>
            <parameters/>
            <steps>
                <step start='1672136489681' status='passed' stop='1672136490535'>
                    <name>I refresh page "/login"</name>
                    <title>I refresh page "/login"</title>
                    <attachments/>
                    <steps/>
                </step>
                <step start='1672136490536' status='passed' stop='1672136490701'>
                    <name>I click "[data-testid="continue-btn"]"</name>
                    <title>I click "[data-testid="continue-btn"]"</title>
                    <attachments/>
                    <steps/>
                </step>
                <step start='1672136490702' status='passed' stop='1672136492702'>
                    <name>I wait 2</name>
                    <title>I wait 2</title>
                    <attachments/>
                    <steps/>
                </step>
                <step start='1672136492702' status='passed' stop='1672136492714'>
                    <name>I see element "[data-testid="email-error"]"</name>
                    <title>I see element "[data-testid="email-error"]"</title>
                    <attachments/>
                    <steps/>
                </step>
                <step start='1672136492714' status='passed' stop='1672136494716'>
                    <name>I wait 2</name>
                    <title>I wait 2</title>
                    <attachments/>
                    <steps/>
                </step>
            </steps>
            <attachments/>
        </test-case>
        <test-case start='1672136494721' status='passed' stop='1672136501337'>
            <name>ForgotPwd_invalid email validation</name>
            <title>ForgotPwd_invalid email validation</title>
            <labels/>
            <parameters/>
            <steps>
                <step start='1672136494726' status='passed' stop='1672136494896'>
                    <name>I click "[href="/forgot_password"]"</name>
                    <title>I click "[href="/forgot_password"]"</title>
                    <attachments/>
                    <steps/>
                </step>
                <step start='1672136494896' status='passed' stop='1672136494932'>
                    <name>I see element ".text-gray-150.mb-8.text-center.sub-text"</name>
                    <title>I see element ".text-gray-150.mb-8.text-center.sub-text"</title>
                    <attachments/>
                    <steps/>
                </step>
                <step start='1672136494932' status='passed' stop='1672136495164'>
                    <name>I fill field "[class="flex flex-col"] [name=email]", "abc@abc"</name>
                    <title>I fill field "[class="flex flex-col"] [name=email]", "abc@abc"</title>
                    <attachments/>
                    <steps/>
                </step>
                <step start='1672136495164' status='passed' stop='1672136497166'>
                    <name>I wait 2</name>
                    <title>I wait 2</title>
                    <attachments/>
                    <steps/>
                </step>
                <step start='1672136497167' status='passed' stop='1672136497322'>
                    <name>I click "[type="submit"]"</name>
                    <title>I click "[type="submit"]"</title>
                    <attachments/>
                    <steps/>
                </step>
                <step start='1672136497323' status='passed' stop='1672136499324'>
                    <name>I wait 2</name>
                    <title>I wait 2</title>
                    <attachments/>
                    <steps/>
                </step>
                <step start='1672136499325' status='passed' stop='1672136499336'>
                    <name>I see element "[data-testid="error-id"]"</name>
                    <title>I see element "[data-testid="error-id"]"</title>
                    <attachments/>
                    <steps/>
                </step>
                <step start='1672136499336' status='passed' stop='1672136501337'>
                    <name>I wait 2</name>
                    <title>I wait 2</title>
                    <attachments/>
                    <steps/>
                </step>
            </steps>
            <attachments/>
        </test-case>
    </test-cases>
</ns2:test-suite>