<?xml version='1.0'?>
<ns2:test-suite xmlns:ns2='urn:model.allure.qatools.yandex.ru' start='1672830096629' stop='1672830113648'>
    <name>login:</name>
    <title>login:</title>
    <test-cases>
        <test-case start='1672830097267' status='passed' stop='1672830113645'>
            <name>PretaaLogin_test</name>
            <title>PretaaLogin_test</title>
            <labels/>
            <parameters/>
            <steps>
                <step start='1672830097773' status='passed' stop='1672830099950'>
                    <name>I am on page "/login"</name>
                    <title>I am on page "/login"</title>
                    <attachments/>
                    <steps/>
                </step>
                <step start='1672830099951' status='passed' stop='1672830099958'>
                    <name>I see "Continue"</name>
                    <title>I see "Continue"</title>
                    <attachments/>
                    <steps/>
                </step>
                <step start='1672830099958' status='passed' stop='1672830100412'>
                    <name>I fill field "[data-testid="email"]", "jiniya+1+admin@itobuz.com"</name>
                    <title>I fill field "[data-testid="email"]", "jiniya+1+admin@itobuz.com"</title>
                    <attachments/>
                    <steps/>
                </step>
                <step start='1672830100413' status='passed' stop='1672830100628'>
                    <name>I click "[data-testid="continue-btn"]"</name>
                    <title>I click "[data-testid="continue-btn"]"</title>
                    <attachments/>
                    <steps/>
                </step>
                <step start='1672830100629' status='passed' stop='1672830103183'>
                    <name>I fill field "[data-testid="password"]", "Password@50"</name>
                    <title>I fill field "[data-testid="password"]", "Password@50"</title>
                    <attachments/>
                    <steps/>
                </step>
                <step start='1672830103183' status='passed' stop='1672830103190'>
                    <name>I see "Show Password"</name>
                    <title>I see "Show Password"</title>
                    <attachments/>
                    <steps/>
                </step>
                <step start='1672830103190' status='passed' stop='1672830104190'>
                    <name>I wait 1</name>
                    <title>I wait 1</title>
                    <attachments/>
                    <steps/>
                </step>
                <step start='1672830104191' status='passed' stop='1672830104336'>
                    <name>I click "[type="button"]"</name>
                    <title>I click "[type="button"]"</title>
                    <attachments/>
                    <steps/>
                </step>
                <step start='1672830104337' status='passed' stop='1672830104501'>
                    <name>I click "[data-testid="submit-btn"]"</name>
                    <title>I click "[data-testid="submit-btn"]"</title>
                    <attachments/>
                    <steps/>
                </step>
                <step start='1672830104501' status='passed' stop='1672830107502'>
                    <name>I wait 3</name>
                    <title>I wait 3</title>
                    <attachments/>
                    <steps/>
                </step>
                <step start='1672830107503' status='passed' stop='1672830107691'>
                    <name>I click "[href="/settings/preferences/profile"]"</name>
                    <title>I click "[href="/settings/preferences/profile"]"</title>
                    <attachments/>
                    <steps/>
                </step>
                <step start='1672830107691' status='passed' stop='1672830107833'>
                    <name>I click ".pl-4 div:nth-child(4) h3"</name>
                    <title>I click ".pl-4 div:nth-child(4) h3"</title>
                    <attachments/>
                    <steps/>
                </step>
                <step start='1672830107834' status='passed' stop='1672830109835'>
                    <name>I wait 2</name>
                    <title>I wait 2</title>
                    <attachments/>
                    <steps/>
                </step>
                <step start='1672830109837' status='passed' stop='1672830109989'>
                    <name>I click "[href="/settings/admin/user-list"]"</name>
                    <title>I click "[href="/settings/admin/user-list"]"</title>
                    <attachments/>
                    <steps/>
                </step>
                <step start='1672830109989' status='passed' stop='1672830111990'>
                    <name>I wait 2</name>
                    <title>I wait 2</title>
                    <attachments/>
                    <steps/>
                </step>
                <step start='1672830111992' status='passed' stop='1672830112151'>
                    <name>I click "[type="submit"]:nth-child(1)"</name>
                    <title>I click "[type="submit"]:nth-child(1)"</title>
                    <attachments/>
                    <steps/>
                </step>
                <step start='1672830112151' status='passed' stop='1672830112294'>
                    <name>I click "[data-test-id="options"]"</name>
                    <title>I click "[data-test-id="options"]"</title>
                    <attachments/>
                    <steps/>
                </step>
                <step start='1672830112294' status='passed' stop='1672830112760'>
                    <name>I see element "[data-test-id="page-title"]"</name>
                    <title>I see element "[data-test-id="page-title"]"</title>
                    <attachments/>
                    <steps/>
                </step>
                <step start='1672830112760' status='passed' stop='1672830113644'>
                    <name>I click "[data-testid="content-frame"] div:nth-child(3) div:nth-child(1) label"</name>
                    <title>I click "[data-testid="content-frame"] div:nth-child(3) div:nth-child(1) label"</title>
                    <attachments/>
                    <steps/>
                </step>
            </steps>
            <attachments/>
        </test-case>
    </test-cases>
</ns2:test-suite>