<?xml version='1.0'?>
<ns2:test-suite xmlns:ns2='urn:model.allure.qatools.yandex.ru' start='1672135702045' stop='1672135733298'>
    <name>pretaa_comments_test:</name>
    <title>pretaa_comments_test:</title>
    <test-cases>
        <test-case start='1672135702045' status='passed' stop='1672135733293'>
            <name>Select random company</name>
            <title>Select random company</title>
            <labels/>
            <parameters/>
            <steps>
                <step start='1672135702050' status='passed' stop='1672135702060'>
                    <name>I see element "[src="./pretaa-logo.png"]"</name>
                    <title>I see element "[src="./pretaa-logo.png"]"</title>
                    <attachments/>
                    <steps/>
                </step>
                <step start='1672135702061' status='passed' stop='1672135702597'>
                    <name>I fill field "[data-testid="email"]", "jiniya+1+admin@itobuz.com"</name>
                    <title>I fill field "[data-testid="email"]", "jiniya+1+admin@itobuz.com"</title>
                    <attachments/>
                    <steps/>
                </step>
                <step start='1672135702597' status='passed' stop='1672135702740'>
                    <name>I click "[data-testid="continue-btn"]"</name>
                    <title>I click "[data-testid="continue-btn"]"</title>
                    <attachments/>
                    <steps/>
                </step>
                <step start='1672135702740' status='passed' stop='1672135704100'>
                    <name>I fill field "[data-testid="password"]", "Password@50"</name>
                    <title>I fill field "[data-testid="password"]", "Password@50"</title>
                    <attachments/>
                    <steps/>
                </step>
                <step start='1672135704100' status='passed' stop='1672135704109'>
                    <name>I see "Show Password"</name>
                    <title>I see "Show Password"</title>
                    <attachments/>
                    <steps/>
                </step>
                <step start='1672135704109' status='passed' stop='1672135705110'>
                    <name>I wait 1</name>
                    <title>I wait 1</title>
                    <attachments/>
                    <steps/>
                </step>
                <step start='1672135705111' status='passed' stop='1672135705244'>
                    <name>I click "[type="button"]"</name>
                    <title>I click "[type="button"]"</title>
                    <attachments/>
                    <steps/>
                </step>
                <step start='1672135705245' status='passed' stop='1672135705380'>
                    <name>I click "[data-testid="submit-btn"]"</name>
                    <title>I click "[data-testid="submit-btn"]"</title>
                    <attachments/>
                    <steps/>
                </step>
                <step start='1672135705380' status='passed' stop='1672135708382'>
                    <name>I wait 3</name>
                    <title>I wait 3</title>
                    <attachments/>
                    <steps/>
                </step>
                <step start='1672135708382' status='passed' stop='1672135708392'>
                    <name>I see "Companies"</name>
                    <title>I see "Companies"</title>
                    <attachments/>
                    <steps/>
                </step>
                <step start='1672135708392' status='passed' stop='1672135708556'>
                    <name>I click "[href="/companies/list"]"</name>
                    <title>I click "[href="/companies/list"]"</title>
                    <attachments/>
                    <steps/>
                </step>
                <step start='1672135708556' status='passed' stop='1672135711558'>
                    <name>I wait 3</name>
                    <title>I wait 3</title>
                    <attachments/>
                    <steps/>
                </step>
                <step start='1672135711558' status='passed' stop='1672135711636'>
                    <name>I grab text from all "[data-test-id="company-row"]"</name>
                    <title>I grab text from all "[data-test-id="company-row"]"</title>
                    <attachments/>
                    <steps/>
                </step>
                <step start='1672135711639' status='passed' stop='1672135712324'>
                    <name>I fill field "[data-testid="search-input"]", "Beatty, Zboncak and Kub Company 17"</name>
                    <title>I fill field "[data-testid="search-input"]", "Beatty, Zboncak and Kub Company 17"</title>
                    <attachments/>
                    <steps/>
                </step>
                <step start='1672135712324' status='passed' stop='1672135714325'>
                    <name>I wait 2</name>
                    <title>I wait 2</title>
                    <attachments/>
                    <steps/>
                </step>
                <step start='1672135714325' status='passed' stop='1672135714488'>
                    <name>I click "Beatty, Zboncak and Kub Company 17"</name>
                    <title>I click "Beatty, Zboncak and Kub Company 17"</title>
                    <attachments/>
                    <steps/>
                </step>
                <step start='1672135714489' status='passed' stop='1672135714652'>
                    <name>I see element "[data-test-id="page-title"]"</name>
                    <title>I see element "[data-test-id="page-title"]"</title>
                    <attachments/>
                    <steps/>
                </step>
                <step start='1672135714653' status='passed' stop='1672135715739'>
                    <name>I see "Beatty, Zboncak and Kub Company 17"</name>
                    <title>I see "Beatty, Zboncak and Kub Company 17"</title>
                    <attachments/>
                    <steps/>
                </step>
                <step start='1672135715739' status='passed' stop='1672135715747'>
                    <name>I see element "[data-test-id="company-list-link"]"</name>
                    <title>I see element "[data-test-id="company-list-link"]"</title>
                    <attachments/>
                    <steps/>
                </step>
                <step start='1672135715748' status='passed' stop='1672135717749'>
                    <name>I wait 2</name>
                    <title>I wait 2</title>
                    <attachments/>
                    <steps/>
                </step>
                <step start='1672135717749' status='passed' stop='1672135717890'>
                    <name>I click "[data-test-id="floating-btn"]"</name>
                    <title>I click "[data-test-id="floating-btn"]"</title>
                    <attachments/>
                    <steps/>
                </step>
                <step start='1672135717890' status='passed' stop='1672135717904'>
                    <name>I see element "[data-test-id="page-title"]"</name>
                    <title>I see element "[data-test-id="page-title"]"</title>
                    <attachments/>
                    <steps/>
                </step>
                <step start='1672135717904' status='passed' stop='1672135722905'>
                    <name>I wait 5</name>
                    <title>I wait 5</title>
                    <attachments/>
                    <steps/>
                </step>
                <step start='1672135722905' status='passed' stop='1672135723088'>
                    <name>I click "[data-testid="launch"] [class="flex items-center"]"</name>
                    <title>I click "[data-testid="launch"] [class="flex items-center"]"</title>
                    <attachments/>
                    <steps/>
                </step>
                <step start='1672135723088' status='passed' stop='1672135723560'>
                    <name>I see element "[data-test-id="page-title"]"</name>
                    <title>I see element "[data-test-id="page-title"]"</title>
                    <attachments/>
                    <steps/>
                </step>
                <step start='1672135723560' status='passed' stop='1672135725561'>
                    <name>I wait 2</name>
                    <title>I wait 2</title>
                    <attachments/>
                    <steps/>
                </step>
                <step start='1672135725561' status='passed' stop='1672135725706'>
                    <name>I click "[alt="filled-icon"]"</name>
                    <title>I click "[alt="filled-icon"]"</title>
                    <attachments/>
                    <steps/>
                </step>
                <step start='1672135725707' status='passed' stop='1672135725872'>
                    <name>I click "//div[@id='react-select-2-option-2']/div/label"</name>
                    <title>I click "//div[@id='react-select-2-option-2']/div/label"</title>
                    <attachments/>
                    <steps/>
                </step>
                <step start='1672135725873' status='passed' stop='1672135725996'>
                    <name>I press key "Enter"</name>
                    <title>I press key "Enter"</title>
                    <attachments/>
                    <steps/>
                </step>
                <step start='1672135725997' status='passed' stop='1672135727997'>
                    <name>I wait 2</name>
                    <title>I wait 2</title>
                    <attachments/>
                    <steps/>
                </step>
                <step start='1672135727998' status='passed' stop='1672135728149'>
                    <name>I click "[type="submit"]"</name>
                    <title>I click "[type="submit"]"</title>
                    <attachments/>
                    <steps/>
                </step>
                <step start='1672135728150' status='passed' stop='1672135728159'>
                    <name>I see "Launch"</name>
                    <title>I see "Launch"</title>
                    <attachments/>
                    <steps/>
                </step>
                <step start='1672135728159' status='passed' stop='1672135728605'>
                    <name>I fill field "[data-test-id="email-input"]", "salma@itobuz.com"</name>
                    <title>I fill field "[data-test-id="email-input"]", "salma@itobuz.com"</title>
                    <attachments/>
                    <steps/>
                </step>
                <step start='1672135728605' status='passed' stop='1672135728785'>
                    <name>I click "[data-testid="preview-btn"]"</name>
                    <title>I click "[data-testid="preview-btn"]"</title>
                    <attachments/>
                    <steps/>
                </step>
                <step start='1672135728785' status='passed' stop='1672135729282'>
                    <name>I click "[data-testid="launch-btn"]"</name>
                    <title>I click "[data-testid="launch-btn"]"</title>
                    <attachments/>
                    <steps/>
                </step>
                <step start='1672135729283' status='passed' stop='1672135731283'>
                    <name>I wait 2</name>
                    <title>I wait 2</title>
                    <attachments/>
                    <steps/>
                </step>
                <step start='1672135731283' status='passed' stop='1672135731291'>
                    <name>I see "Launch Detail"</name>
                    <title>I see "Launch Detail"</title>
                    <attachments/>
                    <steps/>
                </step>
                <step start='1672135731291' status='passed' stop='1672135733293'>
                    <name>I wait 2</name>
                    <title>I wait 2</title>
                    <attachments/>
                    <steps/>
                </step>
            </steps>
            <attachments/>
        </test-case>
    </test-cases>
</ns2:test-suite>