<?xml version='1.0'?>
<ns2:test-suite xmlns:ns2='urn:model.allure.qatools.yandex.ru' start='1672133100860' stop='1672133114378'>
    <name>pretaafeedback_test:</name>
    <title>pretaafeedback_test:</title>
    <test-cases>
        <test-case start='1672133100861' status='passed' stop='1672133114375'>
            <name>feedback_norating</name>
            <title>feedback_norating</title>
            <labels/>
            <parameters/>
            <steps>
                <step start='1672133100866' status='passed' stop='1672133101837'>
                    <name>I am on page "/login"</name>
                    <title>I am on page "/login"</title>
                    <attachments/>
                    <steps/>
                </step>
                <step start='1672133101837' status='passed' stop='1672133102412'>
                    <name>I am on page "/login"</name>
                    <title>I am on page "/login"</title>
                    <attachments/>
                    <steps/>
                </step>
                <step start='1672133102412' status='passed' stop='1672133102421'>
                    <name>I see "Continue"</name>
                    <title>I see "Continue"</title>
                    <attachments/>
                    <steps/>
                </step>
                <step start='1672133102421' status='passed' stop='1672133102950'>
                    <name>I fill field "[data-testid="email"]", "jiniya+1+admin@itobuz.com"</name>
                    <title>I fill field "[data-testid="email"]", "jiniya+1+admin@itobuz.com"</title>
                    <attachments/>
                    <steps/>
                </step>
                <step start='1672133102950' status='passed' stop='1672133103103'>
                    <name>I click "[data-testid="continue-btn"]"</name>
                    <title>I click "[data-testid="continue-btn"]"</title>
                    <attachments/>
                    <steps/>
                </step>
                <step start='1672133103103' status='passed' stop='1672133104457'>
                    <name>I fill field "[data-testid="password"]", "Password@50"</name>
                    <title>I fill field "[data-testid="password"]", "Password@50"</title>
                    <attachments/>
                    <steps/>
                </step>
                <step start='1672133104457' status='passed' stop='1672133104465'>
                    <name>I see "Show Password"</name>
                    <title>I see "Show Password"</title>
                    <attachments/>
                    <steps/>
                </step>
                <step start='1672133104465' status='passed' stop='1672133105466'>
                    <name>I wait 1</name>
                    <title>I wait 1</title>
                    <attachments/>
                    <steps/>
                </step>
                <step start='1672133105467' status='passed' stop='1672133105592'>
                    <name>I click "[type="button"]"</name>
                    <title>I click "[type="button"]"</title>
                    <attachments/>
                    <steps/>
                </step>
                <step start='1672133105592' status='passed' stop='1672133105732'>
                    <name>I click "[data-testid="submit-btn"]"</name>
                    <title>I click "[data-testid="submit-btn"]"</title>
                    <attachments/>
                    <steps/>
                </step>
                <step start='1672133105733' status='passed' stop='1672133108733'>
                    <name>I wait 3</name>
                    <title>I wait 3</title>
                    <attachments/>
                    <steps/>
                </step>
                <step start='1672133108734' status='passed' stop='1672133108752'>
                    <name>I see "Events"</name>
                    <title>I see "Events"</title>
                    <attachments/>
                    <steps/>
                </step>
                <step start='1672133108753' status='passed' stop='1672133108909'>
                    <name>I click "[data-testid="feedback-link"]"</name>
                    <title>I click "[data-testid="feedback-link"]"</title>
                    <attachments/>
                    <steps/>
                </step>
                <step start='1672133108909' status='passed' stop='1672133108918'>
                    <name>I see "Feedback"</name>
                    <title>I see "Feedback"</title>
                    <attachments/>
                    <steps/>
                </step>
                <step start='1672133108918' status='passed' stop='1672133109918'>
                    <name>I wait 1</name>
                    <title>I wait 1</title>
                    <attachments/>
                    <steps/>
                </step>
                <step start='1672133109918' status='passed' stop='1672133109931'>
                    <name>I see "Feedback"</name>
                    <title>I see "Feedback"</title>
                    <attachments/>
                    <steps/>
                </step>
                <step start='1672133109932' status='passed' stop='1672133111932'>
                    <name>I wait 2</name>
                    <title>I wait 2</title>
                    <attachments/>
                    <steps/>
                </step>
                <step start='1672133111932' status='passed' stop='1672133112232'>
                    <name>I fill field "[data-test-id="feedback-comment"]", "test comment"</name>
                    <title>I fill field "[data-test-id="feedback-comment"]", "test comment"</title>
                    <attachments/>
                    <steps/>
                </step>
                <step start='1672133112232' status='passed' stop='1672133112364'>
                    <name>I click "[data-testid="save-btn"]"</name>
                    <title>I click "[data-testid="save-btn"]"</title>
                    <attachments/>
                    <steps/>
                </step>
                <step start='1672133112364' status='passed' stop='1672133114366'>
                    <name>I wait 2</name>
                    <title>I wait 2</title>
                    <attachments/>
                    <steps/>
                </step>
                <step start='1672133114366' status='passed' stop='1672133114375'>
                    <name>I see "Feedback value is a required field"</name>
                    <title>I see "Feedback value is a required field"</title>
                    <attachments/>
                    <steps/>
                </step>
            </steps>
            <attachments/>
        </test-case>
    </test-cases>
</ns2:test-suite>