<?xml version='1.0'?>
<ns2:test-suite xmlns:ns2='urn:model.allure.qatools.yandex.ru' start='1672144148196' stop='1672144175569'>
    <name>pretaacomments_test:</name>
    <title>pretaacomments_test:</title>
    <test-cases>
        <test-case start='1672144148196' status='passed' stop='1672144153725'>
            <name>Invalid email validation</name>
            <title>Invalid email validation</title>
            <labels/>
            <parameters/>
            <steps>
                <step start='1672144148200' status='passed' stop='1672144148767'>
                    <name>I am on page "/login"</name>
                    <title>I am on page "/login"</title>
                    <attachments/>
                    <steps/>
                </step>
                <step start='1672144148767' status='passed' stop='1672144149116'>
                    <name>I fill field "[data-testid="email"]", "123@itobuz.com"</name>
                    <title>I fill field "[data-testid="email"]", "123@itobuz.com"</title>
                    <attachments/>
                    <steps/>
                </step>
                <step start='1672144149116' status='passed' stop='1672144150531'>
                    <name>I click "[data-testid="continue-btn"]"</name>
                    <title>I click "[data-testid="continue-btn"]"</title>
                    <attachments/>
                    <steps/>
                </step>
                <step start='1672144150532' status='passed' stop='1672144151604'>
                    <name>I see element "[data-testid="error-id"]"</name>
                    <title>I see element "[data-testid="error-id"]"</title>
                    <attachments/>
                    <steps/>
                </step>
                <step start='1672144151604' status='passed' stop='1672144153605'>
                    <name>I wait 2</name>
                    <title>I wait 2</title>
                    <attachments/>
                    <steps/>
                </step>
                <step start='1672144153605' status='passed' stop='1672144153724'>
                    <name>I clear field "[data-testid="email"]"</name>
                    <title>I clear field "[data-testid="email"]"</title>
                    <attachments/>
                    <steps/>
                </step>
            </steps>
            <attachments/>
        </test-case>
        <test-case start='1672144153729' status='passed' stop='1672144161148'>
            <name>Password field blank validation</name>
            <title>Password field blank validation</title>
            <labels/>
            <parameters/>
            <steps>
                <step start='1672144153733' status='passed' stop='1672144154138'>
                    <name>I fill field "[data-testid="email"]", "admin@itobuz.com"</name>
                    <title>I fill field "[data-testid="email"]", "admin@itobuz.com"</title>
                    <attachments/>
                    <steps/>
                </step>
                <step start='1672144154138' status='passed' stop='1672144154803'>
                    <name>I click "[data-testid="continue-btn"]"</name>
                    <title>I click "[data-testid="continue-btn"]"</title>
                    <attachments/>
                    <steps/>
                </step>
                <step start='1672144154803' status='passed' stop='1672144156803'>
                    <name>I wait 2</name>
                    <title>I wait 2</title>
                    <attachments/>
                    <steps/>
                </step>
                <step start='1672144156804' status='passed' stop='1672144157953'>
                    <name>I click "[data-testid="submit-btn"]"</name>
                    <title>I click "[data-testid="submit-btn"]"</title>
                    <attachments/>
                    <steps/>
                </step>
                <step start='1672144157953' status='passed' stop='1672144159029'>
                    <name>I see element "[data-testid="error-id"]"</name>
                    <title>I see element "[data-testid="error-id"]"</title>
                    <attachments/>
                    <steps/>
                </step>
                <step start='1672144159029' status='passed' stop='1672144161029'>
                    <name>I wait 2</name>
                    <title>I wait 2</title>
                    <attachments/>
                    <steps/>
                </step>
                <step start='1672144161030' status='passed' stop='1672144161148'>
                    <name>I clear field "[data-testid="email"]"</name>
                    <title>I clear field "[data-testid="email"]"</title>
                    <attachments/>
                    <steps/>
                </step>
            </steps>
            <attachments/>
        </test-case>
        <test-case start='1672144161153' status='passed' stop='1672144167233'>
            <name>Email field blank validation</name>
            <title>Email field blank validation</title>
            <labels/>
            <parameters/>
            <steps>
                <step start='1672144161157' status='passed' stop='1672144162001'>
                    <name>I refresh page "/login"</name>
                    <title>I refresh page "/login"</title>
                    <attachments/>
                    <steps/>
                </step>
                <step start='1672144162001' status='passed' stop='1672144163220'>
                    <name>I click "[data-testid="continue-btn"]"</name>
                    <title>I click "[data-testid="continue-btn"]"</title>
                    <attachments/>
                    <steps/>
                </step>
                <step start='1672144163220' status='passed' stop='1672144165221'>
                    <name>I wait 2</name>
                    <title>I wait 2</title>
                    <attachments/>
                    <steps/>
                </step>
                <step start='1672144165221' status='passed' stop='1672144165231'>
                    <name>I see element "[data-testid="email-error"]"</name>
                    <title>I see element "[data-testid="email-error"]"</title>
                    <attachments/>
                    <steps/>
                </step>
                <step start='1672144165231' status='passed' stop='1672144167233'>
                    <name>I wait 2</name>
                    <title>I wait 2</title>
                    <attachments/>
                    <steps/>
                </step>
            </steps>
            <attachments/>
        </test-case>
        <test-case start='1672144167237' status='passed' stop='1672144175565'>
            <name>ForgotPwd_invalid email validation</name>
            <title>ForgotPwd_invalid email validation</title>
            <labels/>
            <parameters/>
            <steps>
                <step start='1672144167241' status='passed' stop='1672144168423'>
                    <name>I click "[href="/forgot_password"]"</name>
                    <title>I click "[href="/forgot_password"]"</title>
                    <attachments/>
                    <steps/>
                </step>
                <step start='1672144168423' status='passed' stop='1672144168431'>
                    <name>I see element ".text-gray-150.mb-8.text-center.sub-text"</name>
                    <title>I see element ".text-gray-150.mb-8.text-center.sub-text"</title>
                    <attachments/>
                    <steps/>
                </step>
                <step start='1672144168431' status='passed' stop='1672144168663'>
                    <name>I fill field "[class="flex flex-col"] [name=email]", "abc@abc"</name>
                    <title>I fill field "[class="flex flex-col"] [name=email]", "abc@abc"</title>
                    <attachments/>
                    <steps/>
                </step>
                <step start='1672144168663' status='passed' stop='1672144170665'>
                    <name>I wait 2</name>
                    <title>I wait 2</title>
                    <attachments/>
                    <steps/>
                </step>
                <step start='1672144170665' status='passed' stop='1672144171553'>
                    <name>I click "[type="submit"]"</name>
                    <title>I click "[type="submit"]"</title>
                    <attachments/>
                    <steps/>
                </step>
                <step start='1672144171553' status='passed' stop='1672144173554'>
                    <name>I wait 2</name>
                    <title>I wait 2</title>
                    <attachments/>
                    <steps/>
                </step>
                <step start='1672144173554' status='passed' stop='1672144173563'>
                    <name>I see element "[data-testid="error-id"]"</name>
                    <title>I see element "[data-testid="error-id"]"</title>
                    <attachments/>
                    <steps/>
                </step>
                <step start='1672144173563' status='passed' stop='1672144175564'>
                    <name>I wait 2</name>
                    <title>I wait 2</title>
                    <attachments/>
                    <steps/>
                </step>
            </steps>
            <attachments/>
        </test-case>
    </test-cases>
</ns2:test-suite>